dc_prometheus/__init__.py
dc_prometheus/logcog.py
dc_prometheus-1.3.1.dist-info/LICENSE
dc_prometheus-1.3.1.dist-info/METADATA
dc_prometheus-1.3.1.dist-info/WHEEL
dc_prometheus-1.3.1.dist-info/top_level.txt
dc_prometheus-1.3.1.dist-info/RECORD
